glslt-0.7.6.dist-info/METADATA
glslt-0.7.6.dist-info/WHEEL
glslt-0.7.6.dist-info/entry_points.txt
glslt/__init__.py
glslt/glslt.cp311-win_amd64.pyd
glslt-0.7.6.dist-info/RECORD
