Metadata-Version: 2.1
Name: glslt
Version: 0.7.6
Summary: GLSLT Template compiler library
Keywords: glslt,glsl,language,parser,template
Home-Page: https://github.com/alixinne/glslt
Author: Alixinne <alixinne@pm.me>
Author-email: Alixinne <alixinne@pm.me>
License: MIT
Project-URL: Source Code, https://github.com/alixinne/glslt.git
